sphinxcontrib/confluencebuilder/__init__.py
sphinxcontrib/confluencebuilder/__main__.py
sphinxcontrib/confluencebuilder/assets.py
sphinxcontrib/confluencebuilder/builder.py
sphinxcontrib/confluencebuilder/compat.py
sphinxcontrib/confluencebuilder/debug.py
sphinxcontrib/confluencebuilder/directives.py
sphinxcontrib/confluencebuilder/env.py
sphinxcontrib/confluencebuilder/exceptions.py
sphinxcontrib/confluencebuilder/intersphinx.py
sphinxcontrib/confluencebuilder/logger.py
sphinxcontrib/confluencebuilder/manifest.py
sphinxcontrib/confluencebuilder/nodes.py
sphinxcontrib/confluencebuilder/publisher.py
sphinxcontrib/confluencebuilder/py.typed
sphinxcontrib/confluencebuilder/reportbuilder.py
sphinxcontrib/confluencebuilder/rest.py
sphinxcontrib/confluencebuilder/retry.py
sphinxcontrib/confluencebuilder/roles.py
sphinxcontrib/confluencebuilder/singlebuilder.py
sphinxcontrib/confluencebuilder/state.py
sphinxcontrib/confluencebuilder/svg.py
sphinxcontrib/confluencebuilder/transform.py
sphinxcontrib/confluencebuilder/translator.py
sphinxcontrib/confluencebuilder/util.py
sphinxcontrib/confluencebuilder/writer.py
sphinxcontrib/confluencebuilder/cmd/__init__.py
sphinxcontrib/confluencebuilder/cmd/build.py
sphinxcontrib/confluencebuilder/cmd/conntest.py
sphinxcontrib/confluencebuilder/cmd/report.py
sphinxcontrib/confluencebuilder/cmd/wipe.py
sphinxcontrib/confluencebuilder/config/__init__.py
sphinxcontrib/confluencebuilder/config/checks.py
sphinxcontrib/confluencebuilder/config/defaults.py
sphinxcontrib/confluencebuilder/config/env.py
sphinxcontrib/confluencebuilder/config/exceptions.py
sphinxcontrib/confluencebuilder/config/manager.py
sphinxcontrib/confluencebuilder/config/notifications.py
sphinxcontrib/confluencebuilder/config/validation.py
sphinxcontrib/confluencebuilder/locale/__init__.py
sphinxcontrib/confluencebuilder/locale/sphinxcontrib.confluencebuilder.pot
sphinxcontrib/confluencebuilder/locale/ar/LC_MESSAGES/sphinxcontrib.confluencebuilder.mo
sphinxcontrib_confluencebuilder-3.0.0.dist-info/entry_points.txt
sphinxcontrib_confluencebuilder-3.0.0.dist-info/licenses/LICENSE
sphinxcontrib_confluencebuilder-3.0.0.dist-info/licenses/LICENSE-3RD-PARTY
sphinxcontrib_confluencebuilder-3.0.0.dist-info/WHEEL
sphinxcontrib_confluencebuilder-3.0.0.dist-info/METADATA
sphinxcontrib_confluencebuilder-3.0.0.dist-info/RECORD
