Metadata-Version: 2.4
Name: sphinxcontrib-confluencebuilder
Version: 3.0.0
Summary: Sphinx extension to build Atlassian Confluence Storage Markup
Author-email: Anthony Shaw <anthonyshaw@apache.org>, James Knight <git@jdknight.me>
Maintainer-email: James Knight <git@jdknight.me>
Requires-Python: >=3.10
License-Expression: BSD-2-Clause
Classifier: Development Status :: 5 - Production/Stable
Classifier: Environment :: Console
Classifier: Environment :: Web Environment
Classifier: Framework :: Sphinx
Classifier: Framework :: Sphinx :: Extension
Classifier: Intended Audience :: Developers
Classifier: Operating System :: OS Independent
Classifier: Programming Language :: Python
Classifier: Programming Language :: Python :: 3 :: Only
Classifier: Programming Language :: Python :: 3
Classifier: Programming Language :: Python :: 3.10
Classifier: Programming Language :: Python :: 3.11
Classifier: Programming Language :: Python :: 3.12
Classifier: Programming Language :: Python :: 3.13
Classifier: Programming Language :: Python :: 3.14
Classifier: Topic :: Documentation
Classifier: Topic :: Documentation :: Sphinx
Classifier: Topic :: Utilities
License-File: LICENSE
License-File: LICENSE-3RD-PARTY
Requires-Dist: requests>=2.30.0
Requires-Dist: sphinx>=8.0
Project-URL: Documentation, https://sphinxcontrib-confluencebuilder.readthedocs.io
Project-URL: Download, https://pypi.python.org/pypi/sphinxcontrib-confluencebuilder
Project-URL: Source, https://github.com/sphinx-contrib/confluencebuilder
